shrimpy/__init__.py
shrimpy/allocation.py
shrimpy/auth_provider.py
shrimpy/shrimpy_api_client.py
shrimpy/shrimpy_ws_client.py
shrimpy/strategy.py
shrimpy_python-0.0.15.dist-info/LICENSE
shrimpy_python-0.0.15.dist-info/METADATA
shrimpy_python-0.0.15.dist-info/WHEEL
shrimpy_python-0.0.15.dist-info/top_level.txt
shrimpy_python-0.0.15.dist-info/RECORD
