Metadata-Version: 2.1
Name: shrimpy_python
Version: 0.0.15
Summary: The Official Shrimpy API Python Client
Home-page: https://github.com/shrimpy-dev/shrimpy-python
Author: ShrimpyOfficial
Author-email: support@shrimpy.io
License: MIT
Keywords: orderbook,trade,bitcoin,ethereum,BTC,ETH,client,api,wrapper,exchange,crypto,currency,trading,trading-api
Platform: UNKNOWN
Classifier: Programming Language :: Python :: 3
Classifier: License :: OSI Approved :: MIT License
Classifier: Operating System :: OS Independent
